examples/__init__.py
examples/create_dataset_and_training_job.py
examples/local_storage.py
examples/training_inference_pipeline.py
proximl/__init__.py
proximl/__main__.py
proximl/auth.py
proximl/checkpoints.py
proximl/connections.py
proximl/datasets.py
proximl/environments.py
proximl/exceptions.py
proximl/gpu_types.py
proximl/jobs.py
proximl/models.py
proximl/proximl.py
proximl/volumes.py
proximl/cli/__init__.py
proximl/cli/checkpoint.py
proximl/cli/connection.py
proximl/cli/dataset.py
proximl/cli/environment.py
proximl/cli/gpu.py
proximl/cli/model.py
proximl/cli/volume.py
proximl/cli/cloudbender/__init__.py
proximl/cli/cloudbender/data_connector.py
proximl/cli/cloudbender/datastore.py
proximl/cli/cloudbender/device.py
proximl/cli/cloudbender/node.py
proximl/cli/cloudbender/provider.py
proximl/cli/cloudbender/region.py
proximl/cli/cloudbender/service.py
proximl/cli/job/__init__.py
proximl/cli/job/create.py
proximl/cli/project/__init__.py
proximl/cli/project/credential.py
proximl/cli/project/data_connector.py
proximl/cli/project/datastore.py
proximl/cli/project/secret.py
proximl/cli/project/service.py
proximl/cloudbender/__init__.py
proximl/cloudbender/cloudbender.py
proximl/cloudbender/data_connectors.py
proximl/cloudbender/datastores.py
proximl/cloudbender/device_configs.py
proximl/cloudbender/devices.py
proximl/cloudbender/nodes.py
proximl/cloudbender/providers.py
proximl/cloudbender/regions.py
proximl/cloudbender/services.py
proximl/projects/__init__.py
proximl/projects/credentials.py
proximl/projects/data_connectors.py
proximl/projects/datastores.py
proximl/projects/members.py
proximl/projects/projects.py
proximl/projects/secrets.py
proximl/projects/services.py
tests/integration/__init__.py
tests/integration/conftest.py
tests/integration/test_checkpoints_integration.py
tests/integration/test_datasets_integration.py
tests/integration/test_environments_integration.py
tests/integration/test_gpu_types_integration.py
tests/integration/test_jobs_integration.py
proximl-0.5.17.dist-info/LICENSE
proximl-0.5.17.dist-info/METADATA
proximl-0.5.17.dist-info/WHEEL
proximl-0.5.17.dist-info/entry_points.txt
proximl-0.5.17.dist-info/top_level.txt
proximl-0.5.17.dist-info/RECORD
